boxmot/__init__.py
boxmot/tracker_zoo.py
boxmot/appearance/__init__.py
boxmot/appearance/backbones/__init__.py
boxmot/appearance/backbones/hacnn.py
boxmot/appearance/backbones/mlfn.py
boxmot/appearance/backbones/mobilenetv2.py
boxmot/appearance/backbones/osnet.py
boxmot/appearance/backbones/osnet_ain.py
boxmot/appearance/backbones/resnet.py
boxmot/appearance/backbones/clip/__init__.py
boxmot/appearance/backbones/clip/make_model.py
boxmot/appearance/backbones/clip/make_model_clipreid.py
boxmot/appearance/backbones/clip/clip/__init__.py
boxmot/appearance/backbones/clip/clip/bpe_simple_vocab_16e6.txt.gz
boxmot/appearance/backbones/clip/clip/clip.py
boxmot/appearance/backbones/clip/clip/model.py
boxmot/appearance/backbones/clip/clip/simple_tokenizer.py
boxmot/appearance/backbones/clip/config/__init__.py
boxmot/appearance/backbones/clip/config/defaults.py
boxmot/appearance/backbones/clip/config/defaults_base.py
boxmot/appearance/backbones/lmbn/__init__.py
boxmot/appearance/backbones/lmbn/attention.py
boxmot/appearance/backbones/lmbn/bnneck.py
boxmot/appearance/backbones/lmbn/lmbn_n.py
boxmot/appearance/backends/base_backend.py
boxmot/appearance/backends/onnx_backend.py
boxmot/appearance/backends/openvino_backend.py
boxmot/appearance/backends/pytorch_backend.py
boxmot/appearance/backends/tensorrt_backend.py
boxmot/appearance/backends/tflite_backend.py
boxmot/appearance/backends/torchscript_backend.py
boxmot/appearance/exporters/base_exporter.py
boxmot/appearance/exporters/onnx_exporter.py
boxmot/appearance/exporters/openvino_exporter.py
boxmot/appearance/exporters/tensorrt_exporter.py
boxmot/appearance/exporters/tflite_exporter.py
boxmot/appearance/exporters/torchscript_exporter.py
boxmot/appearance/reid/__init__.py
boxmot/appearance/reid/auto_backend.py
boxmot/appearance/reid/config.py
boxmot/appearance/reid/export.py
boxmot/appearance/reid/factory.py
boxmot/appearance/reid/registry.py
boxmot/configs/datasets/MOT17-ablation.yaml
boxmot_with_appoint_id-13.1.4.dist-info/METADATA
boxmot_with_appoint_id-13.1.4.dist-info/WHEEL
boxmot_with_appoint_id-13.1.4.dist-info/entry_points.txt
boxmot_with_appoint_id-13.1.4.dist-info/licenses/LICENSE
boxmot_with_appoint_id-13.1.4.dist-info/RECORD
